pyearthviz/__init__.py
pyearthviz/calculate_ticks_space.py
pyearthviz/create_line_style.py
pyearthviz/formatter.py
pyearthviz/plot_xy_data.py
pyearthviz-0.1.0.dist-info/licenses/LICENSE
pyearthviz-0.1.0.dist-info/METADATA
pyearthviz-0.1.0.dist-info/WHEEL
pyearthviz-0.1.0.dist-info/top_level.txt
pyearthviz-0.1.0.dist-info/RECORD
